[
  {
    "context": "Workspace",
    "bindings": {
      // "shift shift": "file_finder::Toggle"
      "ctrl-'": "terminal_panel::ToggleFocus"
    }
  },
  {
    "context": "Terminal",
    "bindings": {
      "ctrl-'": "workspace::ToggleBottomDock"
    }
  },
  {
    "context": "Editor && vim_mode == normal",
    "bindings": {
      "ctrl-'": "terminal_panel::ToggleFocus",
      "ctrl-h": "workspace::ActivatePaneLeft",
      "ctrl-l": "workspace::ActivatePaneRight",
      "ctrl-k": "workspace::ActivatePaneUp",
      "ctrl-j": "workspace::ActivatePaneDown"
    }
  },
  {
    "context": "Editor && showing_completions",
    "bindings": {
      "enter": "editor::ConfirmCompletion",
      "shift-enter": "editor::ConfirmCompletionReplace",
      "ctrl-y": "editor::ComposeCompletion"
    }
  }
]
